{"cameraMode":{"drawMode":0,"name":"Shaded","section":"Shading Mode"},"sceneLighting":true,"audioPlay":false,"sceneViewState":{"m_AlwaysRefresh":false,"showFog":true,"showSkybox":true,"showFlares":true,"showImageEffects":true,"showParticleSystems":true,"showVisualEffectGraphs":true,"m_FxEnabled":true},"in2DMode":false,"pivot":{"x":2.8470349311828615,"y":-10.542598724365235,"z":1.9465702772140504},"rotation":{"x":0.1702987104654312,"y":0.7923814654350281,"z":-0.25609806180000307,"w":0.5268785953521729},"size":25.03038787841797,"orthographic":false}